ankilol/__init__.py
ankilol/__main__.py
ankilol/anki.py
ankilol/config.ini
ankilol/definitions.py
ankilol/fetcher.py
ankilol/parser.py
ankilol/test/.test_html_parser.py.swp
ankilol/test/__init__.py
ankilol/test/data/html_questions.html
ankilol/test/data/simple_questions.txt
ankilol/test/test_html_parser.py
ankilol/test/test_html_writer.py
ankilol/test/test_text_parser.py
ankilol/test/test_text_writer.py
ankilol/writer.py
ankilol-0.1.0.dist-info/LICENSE
ankilol-0.1.0.dist-info/METADATA
ankilol-0.1.0.dist-info/WHEEL
ankilol-0.1.0.dist-info/RECORD
