Metadata-Version: 2.1
Name: ankilol
Version: 0.1.0
Summary: A system for parsing and creating Anki flashcards from your existing documents
License: MIT
Author: edmundsj
Author-email: jordan.e@berkeley.edu
Requires-Python: >=3.10,<4.0
Classifier: License :: OSI Approved :: MIT License
Classifier: Programming Language :: Python :: 3
Classifier: Programming Language :: Python :: 3.10
Classifier: Programming Language :: Python :: 3.11
Requires-Dist: bs4 (>=0.0.1,<0.0.2)
Requires-Dist: google-api-python-client (>=2.90.0,<3.0.0)
Requires-Dist: google-auth (>=2.20.0,<3.0.0)
Requires-Dist: google-auth-httplib2 (>=0.1.0,<0.2.0)
Requires-Dist: gspread (>=5.9.0,<6.0.0)
Requires-Dist: oauth2client (>=4.1.3,<5.0.0)
Requires-Dist: pytest (>=7.4.0,<8.0.0)
